lifesim/__init__.py
lifesim/core/core.py
lifesim/core/data.py
lifesim/core/modules.py
lifesim/gui/custom_widgets.py
lifesim/gui/spectrum_gui.py
lifesim/instrument/instrument.py
lifesim/instrument/pn_exozodi.py
lifesim/instrument/pn_localzodi.py
lifesim/instrument/pn_star.py
lifesim/instrument/transmission.py
lifesim/optimize/ahgs.py
lifesim/optimize/optimizer.py
lifesim/util/constants.py
lifesim/util/habitable.py
lifesim/util/importer.py
lifesim/util/options.py
lifesim/util/radiation.py
LIFEsim-0.2.32.dist-info/LICENSE
LIFEsim-0.2.32.dist-info/METADATA
LIFEsim-0.2.32.dist-info/WHEEL
LIFEsim-0.2.32.dist-info/top_level.txt
LIFEsim-0.2.32.dist-info/RECORD
