Metadata-Version: 2.1
Name: LIFEsim
Version: 0.2.32
Summary: Simulator software for the Large Interferometer For Exoplanets (LIFE)
Home-page: https://github.com/fdannert/LIFEsim
Author: Felix Dannert, Maurice Ottiger & Sascha Quanz
Author-email: fdannert@ethz.ch
License: GPLv3
Project-URL: Documentation, https://lifesim.readthedocs.io
Keywords: lifesim
Classifier: Development Status :: 3 - Alpha
Classifier: Intended Audience :: Science/Research
Classifier: Topic :: Scientific/Engineering :: Astronomy
Classifier: License :: OSI Approved :: GNU General Public License v3 (GPLv3)
Classifier: Natural Language :: English
Classifier: Programming Language :: Python :: 3.8
Requires-Python: ~=3.8
License-File: LICENSE
Requires-Dist: astropy >=5.2.1
Requires-Dist: matplotlib >=3.7.0
Requires-Dist: numpy >=1.24.2
Requires-Dist: pandas >=1.5.3
Requires-Dist: PyQt5 ==5.15.4
Requires-Dist: tqdm >=4.64.1
Requires-Dist: tables >=3.8.0
Requires-Dist: GitPython >=3.1.32
